
{
    "results": [
    {
    "parliament_name": "ADILABAD",
    "parliament_english": "ADILABAD",
    "total_seats": 7,
    "count_seats": "7",
    "brs_won": "2",
    "brs_lead": "0",
    "inc_won": "1",
    "inc_lead": "0",
    "bjp_won": "4",
    "bjp_lead": "0",
    "aimim_won": "0",
    "aimim_lead": "0",
    "oth_won": "0",
    "oth_lead": "0"
    },
    {
    "parliament_name": "BHUVANAGIR",
    "parliament_english": "BHONGIR",
    "total_seats": 7,
    "count_seats": "7",
    "brs_won": "1",
    "brs_lead": "0",
    "inc_won": "6",
    "inc_lead": "0",
    "bjp_won": "0",
    "bjp_lead": "0",
    "aimim_won": "0",
    "aimim_lead": "0",
    "oth_won": "0",
    "oth_lead": "0"
    },
    {
    "parliament_name": "CHEVELLA",
    "parliament_english": "CHEVELLA",
    "total_seats": 7,
    "count_seats": "7",
    "brs_won": "4",
    "brs_lead": "0",
    "inc_won": "3",
    "inc_lead": "0",
    "bjp_won": "0",
    "bjp_lead": "0",
    "aimim_won": "0",
    "aimim_lead": "0",
    "oth_won": "0",
    "oth_lead": "0"
    },
    {
    "parliament_name": "HYDERABAD",
    "parliament_english": "HYDERABAD",
    "total_seats": 7,
    "count_seats": "7",
    "brs_won": "0",
    "brs_lead": "0",
    "inc_won": "0",
    "inc_lead": "0",
    "bjp_won": "1",
    "bjp_lead": "0",
    "aimim_won": "6",
    "aimim_lead": "0",
    "oth_won": "0",
    "oth_lead": "0"
    },
    {
    "parliament_name": "KARIMNAGAR",
    "parliament_english": "KARIMNAGAR",
    "total_seats": 7,
    "count_seats": "7",
    "brs_won": "3",
    "brs_lead": "0",
    "inc_won": "4",
    "inc_lead": "0",
    "bjp_won": "0",
    "bjp_lead": "0",
    "aimim_won": "0",
    "aimim_lead": "0",
    "oth_won": "0",
    "oth_lead": "0"
    },
    {
    "parliament_name": "KHAMMAM",
    "parliament_english": "KHAMMAM",
    "total_seats": 7,
    "count_seats": "7",
    "brs_won": "0",
    "brs_lead": "0",
    "inc_won": "6",
    "inc_lead": "0",
    "bjp_won": "0",
    "bjp_lead": "0",
    "aimim_won": "0",
    "aimim_lead": "0",
    "oth_won": "1",
    "oth_lead": "0"
    },
    {
    "parliament_name": "MAHABOOBABAD",
    "parliament_english": "MAHABUBABAD",
    "total_seats": 7,
    "count_seats": "7",
    "brs_won": "1",
    "brs_lead": "0",
    "inc_won": "6",
    "inc_lead": "0",
    "bjp_won": "0",
    "bjp_lead": "0",
    "aimim_won": "0",
    "aimim_lead": "0",
    "oth_won": "0",
    "oth_lead": "0"
    },
    {
    "parliament_name": "MAHABUBNAGAR",
    "parliament_english": "MAHBUBNAGAR",
    "total_seats": 7,
    "count_seats": "7",
    "brs_won": "0",
    "brs_lead": "0",
    "inc_won": "7",
    "inc_lead": "0",
    "bjp_won": "0",
    "bjp_lead": "0",
    "aimim_won": "0",
    "aimim_lead": "0",
    "oth_won": "0",
    "oth_lead": "0"
    },
    {
    "parliament_name": "MALKAJGIRI",
    "parliament_english": "MALKAJGIRI",
    "total_seats": 7,
    "count_seats": "7",
    "brs_won": "7",
    "brs_lead": "0",
    "inc_won": "0",
    "inc_lead": "0",
    "bjp_won": "0",
    "bjp_lead": "0",
    "aimim_won": "0",
    "aimim_lead": "0",
    "oth_won": "0",
    "oth_lead": "0"
    },
    {
    "parliament_name": "MEDAK",
    "parliament_english": "MEDAK",
    "total_seats": 7,
    "count_seats": "7",
    "brs_won": "6",
    "brs_lead": "0",
    "inc_won": "1",
    "inc_lead": "0",
    "bjp_won": "0",
    "bjp_lead": "0",
    "aimim_won": "0",
    "aimim_lead": "0",
    "oth_won": "0",
    "oth_lead": "0"
    },
    {
    "parliament_name": "NAGARKURNOOL",
    "parliament_english": "NAGARKURNOOL",
    "total_seats": 7,
    "count_seats": "7",
    "brs_won": "2",
    "brs_lead": "0",
    "inc_won": "5",
    "inc_lead": "0",
    "bjp_won": "0",
    "bjp_lead": "0",
    "aimim_won": "0",
    "aimim_lead": "0",
    "oth_won": "0",
    "oth_lead": "0"
    },
    {
    "parliament_name": "NALGONDA",
    "parliament_english": "NALGONDA",
    "total_seats": 7,
    "count_seats": "7",
    "brs_won": "1",
    "brs_lead": "0",
    "inc_won": "6",
    "inc_lead": "0",
    "bjp_won": "0",
    "bjp_lead": "0",
    "aimim_won": "0",
    "aimim_lead": "0",
    "oth_won": "0",
    "oth_lead": "0"
    },
    {
    "parliament_name": "NIZAMABAD",
    "parliament_english": "NIZAMABAD",
    "total_seats": 7,
    "count_seats": "7",
    "brs_won": "3",
    "brs_lead": "0",
    "inc_won": "2",
    "inc_lead": "0",
    "bjp_won": "2",
    "bjp_lead": "0",
    "aimim_won": "0",
    "aimim_lead": "0",
    "oth_won": "0",
    "oth_lead": "0"
    },
    {
    "parliament_name": "PEDDAPALLI",
    "parliament_english": "PEDDAPALLE",
    "total_seats": 7,
    "count_seats": "7",
    "brs_won": "0",
    "brs_lead": "0",
    "inc_won": "7",
    "inc_lead": "0",
    "bjp_won": "0",
    "bjp_lead": "0",
    "aimim_won": "0",
    "aimim_lead": "0",
    "oth_won": "0",
    "oth_lead": "0"
    },
    {
    "parliament_name": "SECUNDERABAD",
    "parliament_english": "SECUNDRABAD",
    "total_seats": 7,
    "count_seats": "7",
    "brs_won": "6",
    "brs_lead": "0",
    "inc_won": "0",
    "inc_lead": "0",
    "bjp_won": "0",
    "bjp_lead": "0",
    "aimim_won": "1",
    "aimim_lead": "0",
    "oth_won": "0",
    "oth_lead": "0"
    },
    {
    "parliament_name": "WARANGAL",
    "parliament_english": "WARANGAL",
    "total_seats": 7,
    "count_seats": "7",
    "brs_won": "1",
    "brs_lead": "0",
    "inc_won": "6",
    "inc_lead": "0",
    "bjp_won": "0",
    "bjp_lead": "0",
    "aimim_won": "0",
    "aimim_lead": "0",
    "oth_won": "0",
    "oth_lead": "0"
    },
    {
    "parliament_name": "ZAHEERABAD",
    "parliament_english": "ZAHIRABAD",
    "total_seats": 7,
    "count_seats": "7",
    "brs_won": "2",
    "brs_lead": "0",
    "inc_won": "4",
    "inc_lead": "0",
    "bjp_won": "1",
    "bjp_lead": "0",
    "aimim_won": "0",
    "aimim_lead": "0",
    "oth_won": "0",
    "oth_lead": "0"
    }
    ]
    }